odoo/addons/l10n_br_account_payment_brcobranca/README.rst
odoo/addons/l10n_br_account_payment_brcobranca/__init__.py
odoo/addons/l10n_br_account_payment_brcobranca/__manifest__.py
odoo/addons/l10n_br_account_payment_brcobranca/constants/br_cobranca.py
odoo/addons/l10n_br_account_payment_brcobranca/demo/account_journal_demo.xml
odoo/addons/l10n_br_account_payment_brcobranca/demo/account_move_demo.xml
odoo/addons/l10n_br_account_payment_brcobranca/demo/account_payment_mode.xml
odoo/addons/l10n_br_account_payment_brcobranca/i18n/l10n_br_account_payment_brcobranca.pot
odoo/addons/l10n_br_account_payment_brcobranca/i18n/pt_BR.po
odoo/addons/l10n_br_account_payment_brcobranca/migrations/16.0.3.0.0/post-migration.py
odoo/addons/l10n_br_account_payment_brcobranca/models/__init__.py
odoo/addons/l10n_br_account_payment_brcobranca/models/account_journal.py
odoo/addons/l10n_br_account_payment_brcobranca/models/account_move.py
odoo/addons/l10n_br_account_payment_brcobranca/models/account_move_line.py
odoo/addons/l10n_br_account_payment_brcobranca/models/account_payment_line.py
odoo/addons/l10n_br_account_payment_brcobranca/models/account_payment_order.py
odoo/addons/l10n_br_account_payment_brcobranca/models/l10n_br_cnab_config.py
odoo/addons/l10n_br_account_payment_brcobranca/parser/__init__.py
odoo/addons/l10n_br_account_payment_brcobranca/parser/cnab_file_parser.py
odoo/addons/l10n_br_account_payment_brcobranca/readme/CONFIGURE.md
odoo/addons/l10n_br_account_payment_brcobranca/readme/CONTRIBUTORS.md
odoo/addons/l10n_br_account_payment_brcobranca/readme/CREDITS.md
odoo/addons/l10n_br_account_payment_brcobranca/readme/DESCRIPTION.md
odoo/addons/l10n_br_account_payment_brcobranca/readme/HISTORY.md
odoo/addons/l10n_br_account_payment_brcobranca/readme/INSTALL.md
odoo/addons/l10n_br_account_payment_brcobranca/readme/ROADMAP.md
odoo/addons/l10n_br_account_payment_brcobranca/readme/USAGE.md
odoo/addons/l10n_br_account_payment_brcobranca/security/ir.model.access.csv
odoo_addon_l10n_br_account_payment_brcobranca-16.0.6.2.0.dist-info/METADATA
odoo_addon_l10n_br_account_payment_brcobranca-16.0.6.2.0.dist-info/WHEEL
odoo_addon_l10n_br_account_payment_brcobranca-16.0.6.2.0.dist-info/top_level.txt
odoo_addon_l10n_br_account_payment_brcobranca-16.0.6.2.0.dist-info/RECORD
