Metadata-Version: 2.1
Name: odoo-addon-l10n_br_account_payment_brcobranca
Version: 16.0.6.2.0
Requires-Python: >=3.10
Requires-Dist: erpbrasil.base
Requires-Dist: odoo-addon-account_move_base_import>=16.0dev,<16.1dev
Requires-Dist: odoo-addon-l10n_br_account_payment_order>=16.0dev,<16.1dev
Requires-Dist: odoo>=16.0a,<16.1dev
Summary: receivable Boletos and CNAB using the BRCobranca lib
Home-page: https://github.com/OCA/l10n-brazil
License: AGPL-3
Author: Akretion, Odoo Community Association (OCA)
Author-email: support@odoo-community.org
Classifier: Programming Language :: Python
Classifier: Framework :: Odoo
Classifier: Framework :: Odoo :: 16.0
Classifier: License :: OSI Approved :: GNU Affero General Public License v3
